<?xml version="1.0" encoding="UTF-8" ?><tv date="20230213">
<channel id="AdriaMusicTelevision.de"><display-name>Adria Music Television</display-name><icon src="https://i.imgur.com/QoDpnKg.png"/><url>https://tv.blue.ch</url></channel>
<channel id="CMCTV.hr"><display-name>CMC TV</display-name><icon src="https://i.imgur.com/EZtflIa.png"/><url>https://tv.blue.ch</url></channel>
<channel id="HRT1.hr"><display-name>HRT 1</display-name><icon src="https://i.imgur.com/lDSctzX.png"/><url>https://tv.blue.ch</url></channel>
<channel id="HRTInternational.hr"><display-name>HRT International</display-name><icon src="https://i.imgur.com/Bua4yif.png"/><url>https://tv.blue.ch</url></channel>
<channel id="Z1.hr"><display-name>Z1</display-name><icon src="https://i.imgur.com/k8OBcG1.png"/><url>https://tv.blue.ch</url></channel>
<programme start="20230212200000 +0000" stop="20230213050000 +0000" channel="AdriaMusicTelevision.de"><title lang="hr">MRAK LISTA</title><desc lang="hr">Različite tematske emisije, novi izvođači, pjevanje gledatelja, ljestvice, izbor alternativne glazbe s područja regije Adria.</desc><icon src="https://services.sg101.prd.sctv.ch/content/images/tv/broadcast/1949/300.307_genre_w1920.webp"/></programme>
<programme start="20230213050000 +0000" stop="20230213070000 +0000" channel="AdriaMusicTelevision.de"><title lang="hr">LAGANO BUĐENJE</title><desc lang="hr">Jutarnji izbor glazbe i naš voditelj povesti će vas u novi dan. Zanimljive novosti, tračevi i poneka ozbiljna priča uljepšati će vam buđenje.</desc><icon src="https://services.sg101.prd.sctv.ch/content/images/tv/broadcast/1949/300.307_genre_w1920.webp"/></programme>
<programme start="20230213070000 +0000" stop="20230213090000 +0000" channel="AdriaMusicTelevision.de"><title lang="hr">UHVATI RITAM</title><desc lang="hr">Izbor starih i novih hitova s područja regije Adria. Uhvatite ritam dana s najvećim izvođačima uz različite voditelje uživo.</desc><icon src="https://services.sg101.prd.sctv.ch/content/images/tv/broadcast/1949/300.307_genre_w1920.webp"/></programme>
<programme start="20230213090000 +0000" stop="20230213110000 +0000" channel="AdriaMusicTelevision.de"><title lang="hr">U SRIDU</title><desc lang="hr">Trenutačno najpopularniji izvođači najslušanije glazbe. Intervju s popularnim izvođačima, predstavljanja novih emisija i videospotova uživo s voditeljem.</desc><icon src="https://services.sg101.prd.sctv.ch/content/images/tv/broadcast/1949/300.307_genre_w1920.webp"/></programme>
<programme start="20230213110000 +0000" stop="20230213130000 +0000" channel="AdriaMusicTelevision.de"><title lang="hr">ZA DOBRA STARA VREMENA</title><desc lang="hr">Brižno odabrane pjesme koje će stvoriti odličnu atmosferu bez obzira na to što radite. Svima dobro poznati ritmovi i melodije koje smo slušali još sa svojim roditeljima.</desc><icon src="https://services.sg101.prd.sctv.ch/content/images/tv/broadcast/1949/300.307_genre_w1920.webp"/></programme>
<programme start="20230213130000 +0000" stop="20230213200000 +0000" channel="AdriaMusicTelevision.de"><title lang="hr">MI PLEŠEMO</title><desc lang="hr">Opusti dušu i tijelo nakon napornog radnog dana ili priredi popodnevnu vikend zabavu uz Adria Music Television. Zapjevaj, viči i mrdaj.</desc><icon src="https://services.sg101.prd.sctv.ch/content/images/tv/broadcast/1949/300.307_genre_w1920.webp"/></programme>
<programme start="20230213200000 +0000" stop="20230214050000 +0000" channel="AdriaMusicTelevision.de"><title lang="hr">MRAK LISTA</title><desc lang="hr">Različite tematske emisije, novi izvođači, pjevanje gledatelja, ljestvice, izbor alternativne glazbe s područja regije Adria.</desc><icon src="https://services.sg101.prd.sctv.ch/content/images/tv/broadcast/1949/300.307_genre_w1920.webp"/></programme>
<programme start="20230214050000 +0000" stop="20230214070000 +0000" channel="AdriaMusicTelevision.de"><title lang="hr">LAGANO BUĐENJE</title><desc lang="hr">Jutarnji izbor glazbe i naš voditelj povesti će vas u novi dan. Zanimljive novosti, tračevi i poneka ozbiljna priča uljepšati će vam buđenje.</desc><icon src="https://services.sg101.prd.sctv.ch/content/images/tv/broadcast/1949/300.307_genre_w1920.webp"/></programme>
<programme start="20230214070000 +0000" stop="20230214090000 +0000" channel="AdriaMusicTelevision.de"><title lang="hr">UHVATI RITAM</title><desc lang="hr">Izbor starih i novih hitova s područja regije Adria. Uhvatite ritam dana s najvećim izvođačima uz različite voditelje uživo.</desc><icon src="https://services.sg101.prd.sctv.ch/content/images/tv/broadcast/1949/300.307_genre_w1920.webp"/></programme>
<programme start="20230214090000 +0000" stop="20230214110000 +0000" channel="AdriaMusicTelevision.de"><title lang="hr">U SRIDU</title><desc lang="hr">Trenutačno najpopularniji izvođači najslušanije glazbe. Intervju s popularnim izvođačima, predstavljanja novih emisija i videospotova uživo s voditeljem.</desc><icon src="https://services.sg101.prd.sctv.ch/content/images/tv/broadcast/1949/300.307_genre_w1920.webp"/></programme>
<programme start="20230214110000 +0000" stop="20230214130000 +0000" channel="AdriaMusicTelevision.de"><title lang="hr">ZA DOBRA STARA VREMENA</title><desc lang="hr">Brižno odabrane pjesme koje će stvoriti odličnu atmosferu bez obzira na to što radite. Svima dobro poznati ritmovi i melodije koje smo slušali još sa svojim roditeljima.</desc><icon src="https://services.sg101.prd.sctv.ch/content/images/tv/broadcast/1949/300.307_genre_w1920.webp"/></programme>
<programme start="20230214130000 +0000" stop="20230214200000 +0000" channel="AdriaMusicTelevision.de"><title lang="hr">MI PLEŠEMO</title><desc lang="hr">Opusti dušu i tijelo nakon napornog radnog dana ili priredi popodnevnu vikend zabavu uz Adria Music Television. Zapjevaj, viči i mrdaj.</desc><icon src="https://services.sg101.prd.sctv.ch/content/images/tv/broadcast/1949/300.307_genre_w1920.webp"/></programme>
<programme start="20230214200000 +0000" stop="20230215050000 +0000" channel="AdriaMusicTelevision.de"><title lang="hr">MRAK LISTA</title><desc lang="hr">Različite tematske emisije, novi izvođači, pjevanje gledatelja, ljestvice, izbor alternativne glazbe s područja regije Adria.</desc><icon src="https://services.sg101.prd.sctv.ch/content/images/tv/broadcast/1949/300.307_genre_w1920.webp"/></programme>
<programme start="20230212220000 +0000" stop="20230213020000 +0000" channel="CMCTV.hr"><title lang="hr">Hitovi</title><icon src="https://services.sg101.prd.sctv.ch/content/images/tv/broadcast/112/300.311_genre_w1920.webp"/></programme>
<programme start="20230213020000 +0000" stop="20230213050000 +0000" channel="CMCTV.hr"><title lang="hr">Nocna straza</title><icon src="https://services.sg101.prd.sctv.ch/content/images/tv/broadcast/112/700.709_genre_w1920.webp"/></programme>
<programme start="20230213050000 +0000" stop="20230213080000 +0000" channel="CMCTV.hr"><title lang="hr">Dobro jutro!</title><icon src="https://services.sg101.prd.sctv.ch/content/images/tv/broadcast/112/700.701_genre_w1920.webp"/></programme>
<programme start="20230213080000 +0000" stop="20230213081500 +0000" channel="CMCTV.hr"><title lang="hr">Vijesti</title><desc lang="hr">Vijesti.</desc><icon src="https://services.sg101.prd.sctv.ch/content/images/tv/broadcast/112/700.701_genre_w1920.webp"/></programme>
<programme start="20230213081500 +0000" stop="20230213090000 +0000" channel="CMCTV.hr"><title lang="hr">100 hitovi</title><icon src="https://services.sg101.prd.sctv.ch/content/images/tv/broadcast/112/300.311_genre_w1920.webp"/></programme>
<programme start="20230213090000 +0000" stop="20230213110000 +0000" channel="CMCTV.hr"><title lang="hr">Hitovi</title><icon src="https://services.sg101.prd.sctv.ch/content/images/tv/broadcast/112/300.311_genre_w1920.webp"/></programme>
<programme start="20230213110000 +0000" stop="20230213111500 +0000" channel="CMCTV.hr"><title lang="hr">Autorica - Vjekoslava Huljić</title><icon src="https://services.sg101.prd.sctv.ch/content/images/tv/broadcast/112/300.399_genre_w1920.webp"/></programme>
<programme start="20230213111500 +0000" stop="20230213150000 +0000" channel="CMCTV.hr"><title lang="hr">Dobar Dan</title><desc lang="hr">Sedamnaestogodisnja Cécile provodi ljeto na Francuskoj rivijeri, s ocem i njegovom ljubavnicom Elsom. Raymond je zavodnik, bogat i amoralan covjek iza kojega su brojne povrsne veze s mondenim mladim djevojkama. No, on i Cécile dobro se slazu.</desc><icon src="https://services.sg101.prd.sctv.ch/content/images/tv/broadcast/112/100.199_genre_w1920.webp"/></programme>
<programme start="20230213150000 +0000" stop="20230213160000 +0000" channel="CMCTV.hr"><title lang="hr">100 hitovi</title><icon src="https://services.sg101.prd.sctv.ch/content/images/tv/broadcast/112/300.311_genre_w1920.webp"/></programme>
<programme start="20230213160000 +0000" stop="20230213170000 +0000" channel="CMCTV.hr"><title lang="hr">Hitovi</title><icon src="https://services.sg101.prd.sctv.ch/content/images/tv/broadcast/112/300.311_genre_w1920.webp"/></programme>
<programme start="20230213170000 +0000" stop="20230213174500 +0000" channel="CMCTV.hr"><title lang="hr">Top 30</title><icon src="https://services.sg101.prd.sctv.ch/content/images/tv/broadcast/112/700.709_genre_w1920.webp"/></programme>
<programme start="20230213174500 +0000" stop="20230213180000 +0000" channel="CMCTV.hr"><title lang="hr">Mix</title><icon src="https://services.sg101.prd.sctv.ch/content/images/tv/broadcast/112/300.311_genre_w1920.webp"/></programme>
<programme start="20230213180000 +0000" stop="20230213181500 +0000" channel="CMCTV.hr"><title lang="hr">Vijesti</title><desc lang="hr">Vijesti.</desc><icon src="https://services.sg101.prd.sctv.ch/content/images/tv/broadcast/112/700.701_genre_w1920.webp"/></programme>
<programme start="20230213181500 +0000" stop="20230213190000 +0000" channel="CMCTV.hr"><title lang="hr">100 hitovi</title><icon src="https://services.sg101.prd.sctv.ch/content/images/tv/broadcast/112/300.311_genre_w1920.webp"/></programme>
<programme start="20230213190000 +0000" stop="20230213210000 +0000" channel="CMCTV.hr"><title lang="hr">Hitovi</title><icon src="https://services.sg101.prd.sctv.ch/content/images/tv/broadcast/112/300.311_genre_w1920.webp"/></programme>
<programme start="20230213210000 +0000" stop="20230213230000 +0000" channel="CMCTV.hr"><title lang="hr">CMC Party</title><icon src="https://services.sg101.prd.sctv.ch/content/images/tv/broadcast/112/700.701_genre_w1920.webp"/></programme>
<programme start="20230213230000 +0000" stop="20230213231500 +0000" channel="CMCTV.hr"><title lang="hr">Vijesti</title><desc lang="hr">Vijesti.</desc><icon src="https://services.sg101.prd.sctv.ch/content/images/tv/broadcast/112/700.701_genre_w1920.webp"/></programme>
<programme start="20230213231500 +0000" stop="20230214000000 +0000" channel="CMCTV.hr"><title lang="hr">CMC Party</title><icon src="https://services.sg101.prd.sctv.ch/content/images/tv/broadcast/112/700.701_genre_w1920.webp"/></programme>
<programme start="20230214000000 +0000" stop="20230214020000 +0000" channel="CMCTV.hr"><title lang="hr">Hitovi</title><icon src="https://services.sg101.prd.sctv.ch/content/images/tv/broadcast/112/300.311_genre_w1920.webp"/></programme>
<programme start="20230214020000 +0000" stop="20230214030000 +0000" channel="CMCTV.hr"><title lang="hr">Nocna straza</title><icon src="https://services.sg101.prd.sctv.ch/content/images/tv/broadcast/112/700.709_genre_w1920.webp"/></programme>
<programme start="20230214030000 +0000" stop="20230214034500 +0000" channel="CMCTV.hr"><title lang="hr">Top 40</title><icon src="https://services.sg101.prd.sctv.ch/content/images/tv/broadcast/112/700.709_genre_w1920.webp"/></programme>
<programme start="20230214034500 +0000" stop="20230214050000 +0000" channel="CMCTV.hr"><title lang="hr">Nocna straza</title><icon src="https://services.sg101.prd.sctv.ch/content/images/tv/broadcast/112/700.709_genre_w1920.webp"/></programme>
<programme start="20230214050000 +0000" stop="20230214090000 +0000" channel="CMCTV.hr"><title lang="hr">Nocna straza</title><icon src="https://services.sg101.prd.sctv.ch/content/images/tv/broadcast/112/700.709_genre_w1920.webp"/></programme>
<programme start="20230214090000 +0000" stop="20230214154500 +0000" channel="CMCTV.hr"><title lang="hr">Nocna straza</title><icon src="https://services.sg101.prd.sctv.ch/content/images/tv/broadcast/112/700.709_genre_w1920.webp"/></programme>
<programme start="20230214154500 +0000" stop="20230214170000 +0000" channel="CMCTV.hr"><title lang="hr">Nocna straza</title><icon src="https://services.sg101.prd.sctv.ch/content/images/tv/broadcast/112/700.709_genre_w1920.webp"/></programme>
<programme start="20230214170000 +0000" stop="20230214210000 +0000" channel="CMCTV.hr"><title lang="hr">Nocna straza</title><icon src="https://services.sg101.prd.sctv.ch/content/images/tv/broadcast/112/700.709_genre_w1920.webp"/></programme>
<programme start="20230214210000 +0000" stop="20230215010000 +0000" channel="CMCTV.hr"><title lang="hr">Nocna straza</title><icon src="https://services.sg101.prd.sctv.ch/content/images/tv/broadcast/112/700.709_genre_w1920.webp"/></programme>
<programme start="20230212230800 +0000" stop="20230213000000 +0000" channel="HRT1.hr"><title lang="hr">Najveća graditeljska čuda svijeta</title><desc lang="hr">Ove metropole i gradovi posebna su mjesta na kojima prošlost živi ravnopravno sa sadašnjošću, stvarajući kulture jedinstvene za određene narode i njihove dijelove svijeta.</desc><icon src="https://services.sg101.prd.sctv.ch/content/images/tv/broadcast/206/400.414_genre_w1920.webp"/></programme>
<programme start="20230213000000 +0000" stop="20230213011900 +0000" channel="HRT1.hr"><title lang="hr">Opet je Dan zaljubljenih</title><desc lang="hr">Ljubavni film. Iza Katherine je najgore Valentinovo u životu jer čini se da ju je netko začarao. Ubrzo shvaća da je prisiljena uvijek iznova proživljavati isti dan sve dok ne pronađe onog pravog...</desc><icon src="https://services.sg101.prd.sctv.ch/content/images/tv/program/206/p13664999bdh8ab_Backdrop_w1920.webp"/></programme>
<programme start="20230213011900 +0000" stop="20230213014200 +0000" channel="HRT1.hr"><title lang="hr">Goldbergovi</title><desc lang="hr">Stižu proljetni praznici. Barry nagovara Ericu, Ren (K. Berglund) i dečke da uplate jeftini aranžman. Beverly se ne miri s time da Adam neće upisati fakultet odmah nakon završetka srednje škole.</desc></programme>
<programme start="20230213014200 +0000" stop="20230213020600 +0000" channel="HRT1.hr"><title lang="hr">Goldbergovi</title><desc lang="hr">Stižu proljetni praznici. Barry nagovara Ericu, Ren (K. Berglund) i dečke da uplate jeftini aranžman. Beverly se ne miri s time da Adam neće upisati fakultet odmah nakon završetka srednje škole.</desc></programme>
<programme start="20230213020600 +0000" stop="20230213025900 +0000" channel="HRT1.hr"><title lang="hr">Dnevnik 2</title><desc lang="hr">Dnevnik 2.</desc><icon src="https://services.sg101.prd.sctv.ch/content/images/tv/broadcast/206/700.701_genre_w1920.webp"/></programme>
<programme start="20230213025900 +0000" stop="20230213030700 +0000" channel="HRT1.hr"><title lang="hr">Vijesti iz kulture</title><desc lang="hr">Pregled najaktualnijih vijesti iz svijeta kulture.</desc><icon src="https://services.sg101.prd.sctv.ch/content/images/tv/broadcast/206/700.701_genre_w1920.webp"/></programme>
<programme start="20230213030700 +0000" stop="20230213034700 +0000" channel="HRT1.hr"><title lang="hr">Dr. Beck</title></programme>
<programme start="20230213034700 +0000" stop="20230213040000 +0000" channel="HRT1.hr"><title lang="hr">Skica za portret</title><desc lang="hr">Biografije nekih manje poznatih ljudi koji su pridonijeli hrvatskoj kulturi i povijesti.</desc><icon src="https://services.sg101.prd.sctv.ch/content/images/tv/broadcast/206/400.412_genre_w1920.webp"/></programme>
<programme start="20230213040000 +0000" stop="20230213041500 +0000" channel="HRT1.hr"><title lang="hr">Fotografija u Hrvatskoj</title><desc lang="hr">Fotografija u Hrvatskoj.</desc><icon src="https://services.sg101.prd.sctv.ch/content/images/tv/broadcast/206/400.403_genre_w1920.webp"/></programme>
<programme start="20230213041500 +0000" stop="20230213044000 +0000" channel="HRT1.hr"><title lang="hr">Treca Dob</title><desc lang="hr">Treca Dob.</desc><icon src="https://services.sg101.prd.sctv.ch/content/images/tv/broadcast/206/700.701_genre_w1920.webp"/></programme>
<programme start="20230213044000 +0000" stop="20230213052400 +0000" channel="HRT1.hr"><title lang="hr">Betty I Njezine Dijagnoze</title><desc lang="hr">Betty i njezine dijagnoze njemacka je igrana serija medicinske tematike, videna ocima medicinskih sestara sa snaznim zenskim likom u sredistu. To je odlucna i sposobna sestra Bettina Betty Dewald, zaposlena u Karlovoj klinici u Aachenu.</desc><icon src="https://services.sg101.prd.sctv.ch/content/images/tv/program/206/p11357702ih10ah_Iconic_w1920.webp"/></programme>
<programme start="20230213052400 +0000" stop="20230213054500 +0000" channel="HRT1.hr"><title lang="hr">TV kalendar</title><desc lang="hr">Podsjetnik onima koji znaju, a putokaz onima koji zele znati vise.</desc><icon src="https://services.sg101.prd.sctv.ch/content/images/tv/broadcast/206/400.412_genre_w1920.webp"/></programme>
<programme start="20230213054500 +0000" stop="20230213060000 +0000" channel="HRT1.hr"><title lang="hr">Dobro Jutro, Hrvatska</title><icon src="https://services.sg101.prd.sctv.ch/content/images/tv/broadcast/206/400.403_genre_w1920.webp"/></programme>
<programme start="20230213060000 +0000" stop="20230213061300 +0000" channel="HRT1.hr"><title lang="hr">Vijesti</title><desc lang="hr">Vijesti.</desc><icon src="https://services.sg101.prd.sctv.ch/content/images/tv/broadcast/206/700.701_genre_w1920.webp"/></programme>
<programme start="20230213061300 +0000" stop="20230213070000 +0000" channel="HRT1.hr"><title lang="hr">Dobro Jutro, Hrvatska</title><icon src="https://services.sg101.prd.sctv.ch/content/images/tv/broadcast/206/400.403_genre_w1920.webp"/></programme>
<programme start="20230213070000 +0000" stop="20230213071300 +0000" channel="HRT1.hr"><title lang="hr">Vijesti</title><desc lang="hr">Vijesti.</desc><icon src="https://services.sg101.prd.sctv.ch/content/images/tv/broadcast/206/700.701_genre_w1920.webp"/></programme>
<programme start="20230213071300 +0000" stop="20230213080000 +0000" channel="HRT1.hr"><title lang="hr">Dobro Jutro, Hrvatska</title><icon src="https://services.sg101.prd.sctv.ch/content/images/tv/broadcast/206/400.403_genre_w1920.webp"/></programme>
<programme start="20230213080000 +0000" stop="20230213081300 +0000" channel="HRT1.hr"><title lang="hr">Vijesti</title><desc lang="hr">Vijesti.</desc><icon src="https://services.sg101.prd.sctv.ch/content/images/tv/broadcast/206/700.701_genre_w1920.webp"/></programme>
<programme start="20230213081300 +0000" stop="20230213090900 +0000" channel="HRT1.hr"><title lang="hr">Dobro jutro, Hrvatska</title><desc lang="hr">Nasi reporteri uzivo s trgova i ulica gradova s aktualnim vijestima i zanimljivim pricama.</desc><icon src="https://services.sg101.prd.sctv.ch/content/images/tv/broadcast/206/700.701_genre_w1920.webp"/></programme>
<programme start="20230213090900 +0000" stop="20230213094000 +0000" channel="HRT1.hr"><title lang="hr">Treca Dob</title><desc lang="hr">Treca Dob.</desc><icon src="https://services.sg101.prd.sctv.ch/content/images/tv/broadcast/206/700.701_genre_w1920.webp"/></programme>
<programme start="20230213094000 +0000" stop="20230213101000 +0000" channel="HRT1.hr"><title lang="hr">Brza jela Mary Berry</title><icon src="https://services.sg101.prd.sctv.ch/content/images/tv/broadcast/206/400.414_genre_w1920.webp"/></programme>
<programme start="20230213101000 +0000" stop="20230213104000 +0000" channel="HRT1.hr"><title lang="hr">Vrtlarica</title><icon src="https://services.sg101.prd.sctv.ch/content/images/tv/broadcast/206/400.403_genre_w1920.webp"/></programme>
<programme start="20230213104000 +0000" stop="20230213110000 +0000" channel="HRT1.hr"><title lang="hr">TV kalendar</title><desc lang="hr">Podsjetnik onima koji znaju, a putokaz onima koji zele znati vise.</desc><icon src="https://services.sg101.prd.sctv.ch/content/images/tv/broadcast/206/400.412_genre_w1920.webp"/></programme>
<programme start="20230213110000 +0000" stop="20230213111500 +0000" channel="HRT1.hr"><title lang="hr">Dnevnik 1</title><desc lang="hr">Vijesti.</desc><icon src="https://services.sg101.prd.sctv.ch/content/images/tv/program/206/p10285107ih10aa_Iconic_w1920.webp"/></programme>
<programme start="20230213111500 +0000" stop="20230213111800 +0000" channel="HRT1.hr"><title lang="hr">Sport</title><desc lang="hr">Sportske vijesti.</desc><icon src="https://services.sg101.prd.sctv.ch/content/images/tv/broadcast/206/700.701_genre_w1920.webp"/></programme>
<programme start="20230213111800 +0000" stop="20230213113000 +0000" channel="HRT1.hr"><title lang="hr">Vrijeme</title><desc lang="hr">Vrijeme.</desc><icon src="https://services.sg101.prd.sctv.ch/content/images/tv/broadcast/206/700.707_genre_w1920.webp"/></programme>
<programme start="20230213113000 +0000" stop="20230213122500 +0000" channel="HRT1.hr"><title lang="hr">Srca divljega Pantanala, telenovela(1/120)</title></programme>
<programme start="20230213122500 +0000" stop="20230213131200 +0000" channel="HRT1.hr"><title lang="hr">Dr. Beck</title></programme>
<programme start="20230213131200 +0000" stop="20230213143400 +0000" channel="HRT1.hr"><title lang="hr">Opet je Dan zaljubljenih</title><desc lang="hr">Ljubavni film. Iza Katherine je najgore Valentinovo u životu jer čini se da ju je netko začarao. Ubrzo shvaća da je prisiljena uvijek iznova proživljavati isti dan sve dok ne pronađe onog pravog...</desc><icon src="https://services.sg101.prd.sctv.ch/content/images/tv/program/206/p13664999bdh8ab_Backdrop_w1920.webp"/></programme>
<programme start="20230213143400 +0000" stop="20230213152300 +0000" channel="HRT1.hr"><title lang="hr">Najveća graditeljska čuda svijeta</title><desc lang="hr">Ove metropole i gradovi posebna su mjesta na kojima prošlost živi ravnopravno sa sadašnjošću, stvarajući kulture jedinstvene za određene narode i njihove dijelove svijeta.</desc><icon src="https://services.sg101.prd.sctv.ch/content/images/tv/broadcast/206/400.414_genre_w1920.webp"/></programme>
<programme start="20230213152300 +0000" stop="20230213153000 +0000" channel="HRT1.hr"><title lang="hr">HAK - promet info</title><desc lang="hr">Promet info.</desc><icon src="https://services.sg101.prd.sctv.ch/content/images/tv/broadcast/206/700.701_genre_w1920.webp"/></programme>
<programme start="20230213153000 +0000" stop="20230213154500 +0000" channel="HRT1.hr"><title lang="hr">Vijesti</title><desc lang="hr">Vijesti.</desc><icon src="https://services.sg101.prd.sctv.ch/content/images/tv/broadcast/206/700.701_genre_w1920.webp"/></programme>
<programme start="20230213154500 +0000" stop="20230213162300 +0000" channel="HRT1.hr"><title lang="hr">Regionalni Dnevnik</title><icon src="https://services.sg101.prd.sctv.ch/content/images/tv/broadcast/206/700.701_genre_w1920.webp"/></programme>
<programme start="20230213162300 +0000" stop="20230213170900 +0000" channel="HRT1.hr"><title lang="hr">Kod Nas Doma</title><desc lang="hr">Kod Nas Doma.</desc><icon src="https://services.sg101.prd.sctv.ch/content/images/tv/broadcast/206/800.801_genre_w1920.webp"/></programme>
<programme start="20230213170900 +0000" stop="20230213175800 +0000" channel="HRT1.hr"><title lang="hr">Potjera</title><desc lang="hr">Potjera nije samo kviz, Potjera je ujedno i utrka u kojoj natjecatelji moraju pobjeci Lovcu.</desc><icon src="https://services.sg101.prd.sctv.ch/content/images/tv/broadcast/206/300.309_genre_w1920.webp"/></programme>
<programme start="20230213175800 +0000" stop="20230213180000 +0000" channel="HRT1.hr"><title lang="hr">Vrijeme</title><desc lang="hr">Vrijeme.</desc><icon src="https://services.sg101.prd.sctv.ch/content/images/tv/broadcast/206/700.707_genre_w1920.webp"/></programme>
<programme start="20230213180000 +0000" stop="20230213191500 +0000" channel="HRT1.hr"><title lang="hr">Dnevnik 2</title><desc lang="hr">Dnevnik 2.</desc><icon src="https://services.sg101.prd.sctv.ch/content/images/tv/broadcast/206/700.701_genre_w1920.webp"/></programme>
<programme start="20230213191500 +0000" stop="20230213201500 +0000" channel="HRT1.hr"><title lang="hr">What&apos;s up Israel</title><icon src="https://services.sg101.prd.sctv.ch/content/images/tv/broadcast/206/400.414_genre_w1920.webp"/></programme>
<programme start="20230213201500 +0000" stop="20230213210000 +0000" channel="HRT1.hr"><title lang="hr">Oblak u službi zakona</title></programme>
<programme start="20230213210000 +0000" stop="20230213213900 +0000" channel="HRT1.hr"><title lang="hr">Otvoreno</title><icon src="https://services.sg101.prd.sctv.ch/content/images/tv/broadcast/206/700.709_genre_w1920.webp"/></programme>
<programme start="20230213213900 +0000" stop="20230213215400 +0000" channel="HRT1.hr"><title lang="hr">Dnevnik 3</title><desc lang="hr">Vijesti.</desc><icon src="https://services.sg101.prd.sctv.ch/content/images/tv/program/206/p10285107ih10aa_Iconic_w1920.webp"/></programme>
<programme start="20230213215400 +0000" stop="20230213215900 +0000" channel="HRT1.hr"><title lang="hr">Sport</title><desc lang="hr">Sportske vijesti.</desc><icon src="https://services.sg101.prd.sctv.ch/content/images/tv/broadcast/206/700.701_genre_w1920.webp"/></programme>
<programme start="20230213215900 +0000" stop="20230213220200 +0000" channel="HRT1.hr"><title lang="hr">Vrijeme</title><desc lang="hr">Vrijeme.</desc><icon src="https://services.sg101.prd.sctv.ch/content/images/tv/broadcast/206/700.707_genre_w1920.webp"/></programme>
<programme start="20230213220200 +0000" stop="20230213221300 +0000" channel="HRT1.hr"><title lang="hr">Vijesti iz kulture</title><desc lang="hr">Pregled najaktualnijih vijesti iz svijeta kulture.</desc><icon src="https://services.sg101.prd.sctv.ch/content/images/tv/broadcast/206/700.701_genre_w1920.webp"/></programme>
<programme start="20230213221300 +0000" stop="20230213234100 +0000" channel="HRT1.hr"><title lang="hr">Hrvatski pravednici</title><icon src="https://services.sg101.prd.sctv.ch/content/images/tv/broadcast/206/400.414_genre_w1920.webp"/></programme>
<programme start="20230213234100 +0000" stop="20230214010600 +0000" channel="HRT1.hr"><title lang="hr">Ljubav u akciji</title><desc lang="hr">Romantična komedija. Stručnjakinja za fitness i zaljubljenica u prirodu koja radi u luksuznom wellnessu mora dovesti nestašnog glumca u formu za snimanje novog akcijskog filma.</desc><icon src="https://services.sg101.prd.sctv.ch/content/images/tv/program/206/p21951654bdh8aa_Backdrop_w1920.webp"/></programme>
<programme start="20230214010600 +0000" stop="20230214012700 +0000" channel="HRT1.hr"><title lang="hr">Goldbergovi</title><desc lang="hr">Stižu proljetni praznici. Barry nagovara Ericu, Ren (K. Berglund) i dečke da uplate jeftini aranžman. Beverly se ne miri s time da Adam neće upisati fakultet odmah nakon završetka srednje škole.</desc></programme>
<programme start="20230214012700 +0000" stop="20230214015000 +0000" channel="HRT1.hr"><title lang="hr">Goldbergovi</title><desc lang="hr">Stižu proljetni praznici. Barry nagovara Ericu, Ren (K. Berglund) i dečke da uplate jeftini aranžman. Beverly se ne miri s time da Adam neće upisati fakultet odmah nakon završetka srednje škole.</desc></programme>
<programme start="20230214015000 +0000" stop="20230214024300 +0000" channel="HRT1.hr"><title lang="hr">Dnevnik 2</title><desc lang="hr">Dnevnik 2.</desc><icon src="https://services.sg101.prd.sctv.ch/content/images/tv/broadcast/206/700.701_genre_w1920.webp"/></programme>
<programme start="20230214024300 +0000" stop="20230214025300 +0000" channel="HRT1.hr"><title lang="hr">Vijesti iz kulture</title><desc lang="hr">Pregled najaktualnijih vijesti iz svijeta kulture.</desc><icon src="https://services.sg101.prd.sctv.ch/content/images/tv/broadcast/206/700.701_genre_w1920.webp"/></programme>
<programme start="20230214025300 +0000" stop="20230214033500 +0000" channel="HRT1.hr"><title lang="hr">Dr. Beck</title></programme>
<programme start="20230214033500 +0000" stop="20230214035000 +0000" channel="HRT1.hr"><title lang="hr">Skica za portret</title><desc lang="hr">Biografije nekih manje poznatih ljudi koji su pridonijeli hrvatskoj kulturi i povijesti.</desc><icon src="https://services.sg101.prd.sctv.ch/content/images/tv/broadcast/206/400.412_genre_w1920.webp"/></programme>
<programme start="20230214035000 +0000" stop="20230214041500 +0000" channel="HRT1.hr"><title lang="hr">Zlatna liga</title><icon src="https://services.sg101.prd.sctv.ch/content/images/tv/broadcast/206/200.225_genre_w1920.webp"/></programme>
<programme start="20230214041500 +0000" stop="20230214052700 +0000" channel="HRT1.hr"><title lang="hr">Betty I Njezine Dijagnoze</title><desc lang="hr">Betty i njezine dijagnoze njemacka je igrana serija medicinske tematike, videna ocima medicinskih sestara sa snaznim zenskim likom u sredistu. To je odlucna i sposobna sestra Bettina Betty Dewald, zaposlena u Karlovoj klinici u Aachenu.</desc><icon src="https://services.sg101.prd.sctv.ch/content/images/tv/program/206/p11357702ih10ah_Iconic_w1920.webp"/></programme>
<programme start="20230214052700 +0000" stop="20230214054500 +0000" channel="HRT1.hr"><title lang="hr">TV kalendar</title><desc lang="hr">Podsjetnik onima koji znaju, a putokaz onima koji zele znati vise.</desc><icon src="https://services.sg101.prd.sctv.ch/content/images/tv/broadcast/206/400.412_genre_w1920.webp"/></programme>
<programme start="20230214054500 +0000" stop="20230214060000 +0000" channel="HRT1.hr"><title lang="hr">Dobro Jutro, Hrvatska</title><icon src="https://services.sg101.prd.sctv.ch/content/images/tv/broadcast/206/400.403_genre_w1920.webp"/></programme>
<programme start="20230214060000 +0000" stop="20230214061300 +0000" channel="HRT1.hr"><title lang="hr">Vijesti</title><desc lang="hr">Vijesti.</desc><icon src="https://services.sg101.prd.sctv.ch/content/images/tv/broadcast/206/700.701_genre_w1920.webp"/></programme>
<programme start="20230214061300 +0000" stop="20230214070000 +0000" channel="HRT1.hr"><title lang="hr">Dobro Jutro, Hrvatska</title><icon src="https://services.sg101.prd.sctv.ch/content/images/tv/broadcast/206/400.403_genre_w1920.webp"/></programme>
<programme start="20230214070000 +0000" stop="20230214071300 +0000" channel="HRT1.hr"><title lang="hr">Vijesti</title><desc lang="hr">Vijesti.</desc><icon src="https://services.sg101.prd.sctv.ch/content/images/tv/broadcast/206/700.701_genre_w1920.webp"/></programme>
<programme start="20230214071300 +0000" stop="20230214080000 +0000" channel="HRT1.hr"><title lang="hr">Dobro Jutro, Hrvatska</title><icon src="https://services.sg101.prd.sctv.ch/content/images/tv/broadcast/206/400.403_genre_w1920.webp"/></programme>
<programme start="20230214080000 +0000" stop="20230214081300 +0000" channel="HRT1.hr"><title lang="hr">Vijesti</title><desc lang="hr">Vijesti.</desc><icon src="https://services.sg101.prd.sctv.ch/content/images/tv/broadcast/206/700.701_genre_w1920.webp"/></programme>
<programme start="20230214081300 +0000" stop="20230214091400 +0000" channel="HRT1.hr"><title lang="hr">Dobro jutro, Hrvatska</title><desc lang="hr">Nasi reporteri uzivo s trgova i ulica gradova s aktualnim vijestima i zanimljivim pricama.</desc><icon src="https://services.sg101.prd.sctv.ch/content/images/tv/broadcast/206/700.701_genre_w1920.webp"/></programme>
<programme start="20230214091400 +0000" stop="20230214094500 +0000" channel="HRT1.hr"><title lang="hr">Zlatna liga</title><icon src="https://services.sg101.prd.sctv.ch/content/images/tv/broadcast/206/200.225_genre_w1920.webp"/></programme>
<programme start="20230214094500 +0000" stop="20230214101400 +0000" channel="HRT1.hr"><title lang="hr">Lidijina Kuhinja</title><desc lang="hr">Alla parmigiana je način pripreme mnogih jela južne Italije u kojima prevladavaju jednostavni, ali intenzivni okusi.</desc><icon src="https://services.sg101.prd.sctv.ch/content/images/tv/broadcast/206/400.414_genre_w1920.webp"/></programme>
<programme start="20230214101400 +0000" stop="20230214104300 +0000" channel="HRT1.hr"><title lang="hr">Vrtlarica: Mirisna Prica</title><desc lang="hr">Vrtlarica: Mirisna Prica.</desc><icon src="https://services.sg101.prd.sctv.ch/content/images/tv/broadcast/206/400.403_genre_w1920.webp"/></programme>
<programme start="20230214104300 +0000" stop="20230214110000 +0000" channel="HRT1.hr"><title lang="hr">TV kalendar</title><desc lang="hr">Podsjetnik onima koji znaju, a putokaz onima koji zele znati vise.</desc><icon src="https://services.sg101.prd.sctv.ch/content/images/tv/broadcast/206/400.412_genre_w1920.webp"/></programme>
<programme start="20230214110000 +0000" stop="20230214111500 +0000" channel="HRT1.hr"><title lang="hr">Dnevnik 1</title><desc lang="hr">Vijesti.</desc><icon src="https://services.sg101.prd.sctv.ch/content/images/tv/program/206/p10285107ih10aa_Iconic_w1920.webp"/></programme>
<programme start="20230214111500 +0000" stop="20230214111800 +0000" channel="HRT1.hr"><title lang="hr">Sport</title><desc lang="hr">Sportske vijesti.</desc><icon src="https://services.sg101.prd.sctv.ch/content/images/tv/broadcast/206/700.701_genre_w1920.webp"/></programme>
<programme start="20230214111800 +0000" stop="20230214112900 +0000" channel="HRT1.hr"><title lang="hr">Vrijeme</title><desc lang="hr">Vrijeme.</desc><icon src="https://services.sg101.prd.sctv.ch/content/images/tv/broadcast/206/700.707_genre_w1920.webp"/></programme>
<programme start="20230214112900 +0000" stop="20230214122200 +0000" channel="HRT1.hr"><title lang="hr">Srca divljega Pantanala, telenovela(1/120)</title></programme>
<programme start="20230214122200 +0000" stop="20230214130500 +0000" channel="HRT1.hr"><title lang="hr">Dr. Beck</title></programme>
<programme start="20230214130500 +0000" stop="20230214143100 +0000" channel="HRT1.hr"><title lang="hr">Ljubav u akciji</title><desc lang="hr">Romantična komedija. Stručnjakinja za fitness i zaljubljenica u prirodu koja radi u luksuznom wellnessu mora dovesti nestašnog glumca u formu za snimanje novog akcijskog filma.</desc><icon src="https://services.sg101.prd.sctv.ch/content/images/tv/program/206/p21951654bdh8aa_Backdrop_w1920.webp"/></programme>
<programme start="20230214143100 +0000" stop="20230214152200 +0000" channel="HRT1.hr"><title lang="hr">Najveća graditeljska čuda svijeta: Epohalne građevine</title><icon src="https://services.sg101.prd.sctv.ch/content/images/tv/broadcast/206/400.414_genre_w1920.webp"/></programme>
<programme start="20230214152200 +0000" stop="20230214153000 +0000" channel="HRT1.hr"><title lang="hr">HAK - promet info</title><desc lang="hr">Promet info.</desc><icon src="https://services.sg101.prd.sctv.ch/content/images/tv/broadcast/206/700.701_genre_w1920.webp"/></programme>
<programme start="20230214153000 +0000" stop="20230214154500 +0000" channel="HRT1.hr"><title lang="hr">Vijesti</title><desc lang="hr">Vijesti.</desc><icon src="https://services.sg101.prd.sctv.ch/content/images/tv/broadcast/206/700.701_genre_w1920.webp"/></programme>
<programme start="20230214154500 +0000" stop="20230214162100 +0000" channel="HRT1.hr"><title lang="hr">Regionalni Dnevnik</title><icon src="https://services.sg101.prd.sctv.ch/content/images/tv/broadcast/206/700.701_genre_w1920.webp"/></programme>
<programme start="20230214162100 +0000" stop="20230214170700 +0000" channel="HRT1.hr"><title lang="hr">Kod Nas Doma</title><desc lang="hr">Kod Nas Doma.</desc><icon src="https://services.sg101.prd.sctv.ch/content/images/tv/broadcast/206/800.801_genre_w1920.webp"/></programme>
<programme start="20230214170700 +0000" stop="20230214175800 +0000" channel="HRT1.hr"><title lang="hr">Potjera</title><desc lang="hr">Potjera nije samo kviz, Potjera je ujedno i utrka u kojoj natjecatelji moraju pobjeci Lovcu.</desc><icon src="https://services.sg101.prd.sctv.ch/content/images/tv/broadcast/206/300.309_genre_w1920.webp"/></programme>
<programme start="20230214175800 +0000" stop="20230214180000 +0000" channel="HRT1.hr"><title lang="hr">Vrijeme</title><desc lang="hr">Vrijeme.</desc><icon src="https://services.sg101.prd.sctv.ch/content/images/tv/broadcast/206/700.707_genre_w1920.webp"/></programme>
<programme start="20230214180000 +0000" stop="20230214191500 +0000" channel="HRT1.hr"><title lang="hr">Dnevnik 2</title><desc lang="hr">Dnevnik 2.</desc><icon src="https://services.sg101.prd.sctv.ch/content/images/tv/broadcast/206/700.701_genre_w1920.webp"/></programme>
<programme start="20230214191500 +0000" stop="20230214201400 +0000" channel="HRT1.hr"><title lang="hr">Pametan kao vrana, hrabar kao jež</title><desc lang="hr">Lisica dolazi s vrhunskom standardnom opremom koja uključuje ugrađeni kompas, parfem s mirisom ljubičice i multifunkcionalni rep.</desc><icon src="https://services.sg101.prd.sctv.ch/content/images/tv/broadcast/206/400.414_genre_w1920.webp"/></programme>
<programme start="20230214201400 +0000" stop="20230214210000 +0000" channel="HRT1.hr"><title lang="hr">Oblak u službi zakona</title></programme>
<programme start="20230214210000 +0000" stop="20230214213900 +0000" channel="HRT1.hr"><title lang="hr">Otvoreno</title><icon src="https://services.sg101.prd.sctv.ch/content/images/tv/broadcast/206/700.709_genre_w1920.webp"/></programme>
<programme start="20230214213900 +0000" stop="20230214215400 +0000" channel="HRT1.hr"><title lang="hr">Dnevnik 3</title><desc lang="hr">Vijesti.</desc><icon src="https://services.sg101.prd.sctv.ch/content/images/tv/program/206/p10285107ih10aa_Iconic_w1920.webp"/></programme>
<programme start="20230214215400 +0000" stop="20230214215900 +0000" channel="HRT1.hr"><title lang="hr">Sport</title><desc lang="hr">Sportske vijesti.</desc><icon src="https://services.sg101.prd.sctv.ch/content/images/tv/broadcast/206/700.701_genre_w1920.webp"/></programme>
<programme start="20230214215900 +0000" stop="20230214220200 +0000" channel="HRT1.hr"><title lang="hr">Vrijeme</title><desc lang="hr">Vrijeme.</desc><icon src="https://services.sg101.prd.sctv.ch/content/images/tv/broadcast/206/700.707_genre_w1920.webp"/></programme>
<programme start="20230214220200 +0000" stop="20230214221500 +0000" channel="HRT1.hr"><title lang="hr">Vijesti iz kulture</title><desc lang="hr">Pregled najaktualnijih vijesti iz svijeta kulture.</desc><icon src="https://services.sg101.prd.sctv.ch/content/images/tv/broadcast/206/700.701_genre_w1920.webp"/></programme>
<programme start="20230214221500 +0000" stop="20230214231500 +0000" channel="HRT1.hr"><title lang="hr">Što je klasik?</title><desc lang="hr">Molièreova Škola za žene nikad nije dosegla popularnost Škrca ili Mizantropa, no bila je prekretnica u njegovu opusu.</desc><icon src="https://services.sg101.prd.sctv.ch/content/images/tv/broadcast/206/300.399_genre_w1920.webp"/></programme>
<programme start="20230214231500 +0000" stop="20230215001000 +0000" channel="HRT1.hr"><title lang="hr">Najveća graditeljska čuda svijeta</title><icon src="https://services.sg101.prd.sctv.ch/content/images/tv/broadcast/206/400.414_genre_w1920.webp"/></programme>
<programme start="20230212235700 +0000" stop="20230213010100 +0000" channel="HRTInternational.hr"><title lang="hr">Peti Dan</title><icon src="https://services.sg101.prd.sctv.ch/content/images/tv/broadcast/1664/300.317_genre_w1920.webp"/></programme>
<programme start="20230213010100 +0000" stop="20230213010900 +0000" channel="HRTInternational.hr"><title lang="hr">Vijesti Na Spanjolskom Jeziku</title><icon src="https://services.sg101.prd.sctv.ch/content/images/tv/broadcast/1664/700.701_genre_w1920.webp"/></programme>
<programme start="20230213010900 +0000" stop="20230213020300 +0000" channel="HRTInternational.hr"><title lang="hr">Dnevnik 2</title><desc lang="hr">Dnevnik 2.</desc><icon src="https://services.sg101.prd.sctv.ch/content/images/tv/broadcast/1664/700.701_genre_w1920.webp"/></programme>
<programme start="20230213020300 +0000" stop="20230213025800 +0000" channel="HRTInternational.hr"><title lang="hr">cuvar Dvorca</title><desc lang="hr">Dramska serija cuvar dvorca redatelja i scenarista Lukasa Nole govori o Hrvatskoj osamdesetih kada se na politickoj sceni dogadaju promjene koje će krajem desetljeća promijeniti mapu Europe.</desc><icon src="https://services.sg101.prd.sctv.ch/content/images/tv/program/1664/p14573479ih8aa_Iconic_w1920.webp"/></programme>
<programme start="20230213025800 +0000" stop="20230213031300 +0000" channel="HRTInternational.hr"><title lang="hr">Manjinski mozaik</title><desc lang="hr">Ponosno se drže običaja i čuvaju tradiciju starog kraja iz kojeg ih je potjeralo siromaštvo i glad.</desc><icon src="https://services.sg101.prd.sctv.ch/content/images/tv/broadcast/1664/400.412_genre_w1920.webp"/></programme>
<programme start="20230213031300 +0000" stop="20230213032200 +0000" channel="HRTInternational.hr"><title lang="hr">Vijesti na engleskom jeziku</title><icon src="https://services.sg101.prd.sctv.ch/content/images/tv/broadcast/1664/700.701_genre_w1920.webp"/></programme>
<programme start="20230213032200 +0000" stop="20230213041800 +0000" channel="HRTInternational.hr"><title lang="hr">Ususret Dori</title><icon src="https://services.sg101.prd.sctv.ch/content/images/tv/broadcast/1664/700.709_genre_w1920.webp"/></programme>
<programme start="20230213041800 +0000" stop="20230213045900 +0000" channel="HRTInternational.hr"><title lang="hr">Globalna Hrvatska HTV</title><icon src="https://services.sg101.prd.sctv.ch/content/images/tv/broadcast/1664/400.414_genre_w1920.webp"/></programme>
<programme start="20230213045900 +0000" stop="20230213052300 +0000" channel="HRTInternational.hr"><title lang="hr">Otkrivamo Hrvatsku</title><icon src="https://services.sg101.prd.sctv.ch/content/images/tv/broadcast/1664/400.414_genre_w1920.webp"/></programme>
<programme start="20230213052300 +0000" stop="20230213054900 +0000" channel="HRTInternational.hr"><title lang="hr">Turizam.hrt</title><desc lang="hr">U kojoj mjeri koronavirus utjeèe na turistièka kretanja? Kakvo je trenutno stanje rezervacija za Hrvatsku, odgaðaju li se putovanja ili èak otkazuju, otkriva turizam.hrt. U emisiji govorimo i o nastavku gradnje turistièkog imid¾a Hrvatske.</desc><icon src="https://services.sg101.prd.sctv.ch/content/images/tv/broadcast/1664/300.399_genre_w1920.webp"/></programme>
<programme start="20230213054900 +0000" stop="20230213055700 +0000" channel="HRTInternational.hr"><title lang="hr">Vijesti Na Njemačkom Jeziku</title><icon src="https://services.sg101.prd.sctv.ch/content/images/tv/broadcast/1664/400.414_genre_w1920.webp"/></programme>
<programme start="20230213055700 +0000" stop="20230213063800 +0000" channel="HRTInternational.hr"><title lang="hr">Sve ce Biti Dobro</title><desc lang="hr">Graevinski poduzetnik Matko Bebi priprema se za prezentaciju projekta Metropolis koja e se graditi u naselju Brezovo. Njegova supruga, lijenica Nevenka Augustini Bebi, uri na posao u Bolnicu Zapad gdje je oekuje operacija.</desc><icon src="https://services.sg101.prd.sctv.ch/content/images/tv/broadcast/1664/400.403_genre_w1920.webp"/></programme>
<programme start="20230213063800 +0000" stop="20230213075700 +0000" channel="HRTInternational.hr"><title lang="hr">Lidija Bajuk Tira Les - Tvornica</title></programme>
<programme start="20230213075700 +0000" stop="20230213090100 +0000" channel="HRTInternational.hr"><title lang="hr">Peti Dan</title><icon src="https://services.sg101.prd.sctv.ch/content/images/tv/broadcast/1664/300.317_genre_w1920.webp"/></programme>
<programme start="20230213090100 +0000" stop="20230213090900 +0000" channel="HRTInternational.hr"><title lang="hr">Vijesti Na Spanjolskom Jeziku</title><icon src="https://services.sg101.prd.sctv.ch/content/images/tv/broadcast/1664/700.701_genre_w1920.webp"/></programme>
<programme start="20230213090900 +0000" stop="20230213100300 +0000" channel="HRTInternational.hr"><title lang="hr">Dnevnik 2</title><desc lang="hr">Dnevnik 2.</desc><icon src="https://services.sg101.prd.sctv.ch/content/images/tv/broadcast/1664/700.701_genre_w1920.webp"/></programme>
<programme start="20230213100300 +0000" stop="20230213105800 +0000" channel="HRTInternational.hr"><title lang="hr">cuvar Dvorca</title><desc lang="hr">Dramska serija cuvar dvorca redatelja i scenarista Lukasa Nole govori o Hrvatskoj osamdesetih kada se na politickoj sceni dogadaju promjene koje će krajem desetljeća promijeniti mapu Europe.</desc><icon src="https://services.sg101.prd.sctv.ch/content/images/tv/program/1664/p14573479ih8aa_Iconic_w1920.webp"/></programme>
<programme start="20230213105800 +0000" stop="20230213111300 +0000" channel="HRTInternational.hr"><title lang="hr">Manjinski mozaik</title><desc lang="hr">Ponosno se drže običaja i čuvaju tradiciju starog kraja iz kojeg ih je potjeralo siromaštvo i glad.</desc><icon src="https://services.sg101.prd.sctv.ch/content/images/tv/broadcast/1664/400.412_genre_w1920.webp"/></programme>
<programme start="20230213111300 +0000" stop="20230213112200 +0000" channel="HRTInternational.hr"><title lang="hr">Vijesti na engleskom jeziku</title><icon src="https://services.sg101.prd.sctv.ch/content/images/tv/broadcast/1664/700.701_genre_w1920.webp"/></programme>
<programme start="20230213112200 +0000" stop="20230213121800 +0000" channel="HRTInternational.hr"><title lang="hr">Ususret Dori</title><icon src="https://services.sg101.prd.sctv.ch/content/images/tv/broadcast/1664/700.709_genre_w1920.webp"/></programme>
<programme start="20230213121800 +0000" stop="20230213125900 +0000" channel="HRTInternational.hr"><title lang="hr">Globalna Hrvatska HTV</title><icon src="https://services.sg101.prd.sctv.ch/content/images/tv/broadcast/1664/400.414_genre_w1920.webp"/></programme>
<programme start="20230213125900 +0000" stop="20230213132300 +0000" channel="HRTInternational.hr"><title lang="hr">Otkrivamo Hrvatsku</title><icon src="https://services.sg101.prd.sctv.ch/content/images/tv/broadcast/1664/400.414_genre_w1920.webp"/></programme>
<programme start="20230213132300 +0000" stop="20230213134900 +0000" channel="HRTInternational.hr"><title lang="hr">Turizam.hrt</title><desc lang="hr">U kojoj mjeri koronavirus utjeèe na turistièka kretanja? Kakvo je trenutno stanje rezervacija za Hrvatsku, odgaðaju li se putovanja ili èak otkazuju, otkriva turizam.hrt. U emisiji govorimo i o nastavku gradnje turistièkog imid¾a Hrvatske.</desc><icon src="https://services.sg101.prd.sctv.ch/content/images/tv/broadcast/1664/300.399_genre_w1920.webp"/></programme>
<programme start="20230213134900 +0000" stop="20230213135700 +0000" channel="HRTInternational.hr"><title lang="hr">Vijesti Na Njemačkom Jeziku</title><icon src="https://services.sg101.prd.sctv.ch/content/images/tv/broadcast/1664/400.414_genre_w1920.webp"/></programme>
<programme start="20230213135700 +0000" stop="20230213143800 +0000" channel="HRTInternational.hr"><title lang="hr">Sve ce Biti Dobro</title><desc lang="hr">Graevinski poduzetnik Matko Bebi priprema se za prezentaciju projekta Metropolis koja e se graditi u naselju Brezovo. Njegova supruga, lijenica Nevenka Augustini Bebi, uri na posao u Bolnicu Zapad gdje je oekuje operacija.</desc><icon src="https://services.sg101.prd.sctv.ch/content/images/tv/broadcast/1664/400.403_genre_w1920.webp"/></programme>
<programme start="20230213143800 +0000" stop="20230213155700 +0000" channel="HRTInternational.hr"><title lang="hr">Lidija Bajuk Tira Les - Tvornica</title></programme>
<programme start="20230213155700 +0000" stop="20230213170100 +0000" channel="HRTInternational.hr"><title lang="hr">Peti Dan</title><icon src="https://services.sg101.prd.sctv.ch/content/images/tv/broadcast/1664/300.317_genre_w1920.webp"/></programme>
<programme start="20230213170100 +0000" stop="20230213170900 +0000" channel="HRTInternational.hr"><title lang="hr">Vijesti Na Spanjolskom Jeziku</title><icon src="https://services.sg101.prd.sctv.ch/content/images/tv/broadcast/1664/700.701_genre_w1920.webp"/></programme>
<programme start="20230213170900 +0000" stop="20230213180300 +0000" channel="HRTInternational.hr"><title lang="hr">Dnevnik 2</title><desc lang="hr">Dnevnik 2.</desc><icon src="https://services.sg101.prd.sctv.ch/content/images/tv/broadcast/1664/700.701_genre_w1920.webp"/></programme>
<programme start="20230213180300 +0000" stop="20230213185800 +0000" channel="HRTInternational.hr"><title lang="hr">cuvar Dvorca</title><desc lang="hr">Dramska serija cuvar dvorca redatelja i scenarista Lukasa Nole govori o Hrvatskoj osamdesetih kada se na politickoj sceni dogadaju promjene koje će krajem desetljeća promijeniti mapu Europe.</desc><icon src="https://services.sg101.prd.sctv.ch/content/images/tv/program/1664/p14573479ih8aa_Iconic_w1920.webp"/></programme>
<programme start="20230213185800 +0000" stop="20230213191300 +0000" channel="HRTInternational.hr"><title lang="hr">Manjinski mozaik</title><desc lang="hr">Ponosno se drže običaja i čuvaju tradiciju starog kraja iz kojeg ih je potjeralo siromaštvo i glad.</desc><icon src="https://services.sg101.prd.sctv.ch/content/images/tv/broadcast/1664/400.412_genre_w1920.webp"/></programme>
<programme start="20230213191300 +0000" stop="20230213192200 +0000" channel="HRTInternational.hr"><title lang="hr">Vijesti na engleskom jeziku</title><icon src="https://services.sg101.prd.sctv.ch/content/images/tv/broadcast/1664/700.701_genre_w1920.webp"/></programme>
<programme start="20230213192200 +0000" stop="20230213201800 +0000" channel="HRTInternational.hr"><title lang="hr">Ususret Dori</title><icon src="https://services.sg101.prd.sctv.ch/content/images/tv/broadcast/1664/700.709_genre_w1920.webp"/></programme>
<programme start="20230213201800 +0000" stop="20230213205900 +0000" channel="HRTInternational.hr"><title lang="hr">Globalna Hrvatska HTV</title><icon src="https://services.sg101.prd.sctv.ch/content/images/tv/broadcast/1664/400.414_genre_w1920.webp"/></programme>
<programme start="20230213205900 +0000" stop="20230213212300 +0000" channel="HRTInternational.hr"><title lang="hr">Otkrivamo Hrvatsku</title><icon src="https://services.sg101.prd.sctv.ch/content/images/tv/broadcast/1664/400.414_genre_w1920.webp"/></programme>
<programme start="20230213212300 +0000" stop="20230213214900 +0000" channel="HRTInternational.hr"><title lang="hr">Turizam.hrt</title><desc lang="hr">U kojoj mjeri koronavirus utjeèe na turistièka kretanja? Kakvo je trenutno stanje rezervacija za Hrvatsku, odgaðaju li se putovanja ili èak otkazuju, otkriva turizam.hrt. U emisiji govorimo i o nastavku gradnje turistièkog imid¾a Hrvatske.</desc><icon src="https://services.sg101.prd.sctv.ch/content/images/tv/broadcast/1664/300.399_genre_w1920.webp"/></programme>
<programme start="20230213214900 +0000" stop="20230213215700 +0000" channel="HRTInternational.hr"><title lang="hr">Vijesti Na Njemačkom Jeziku</title><icon src="https://services.sg101.prd.sctv.ch/content/images/tv/broadcast/1664/400.414_genre_w1920.webp"/></programme>
<programme start="20230213215700 +0000" stop="20230213223800 +0000" channel="HRTInternational.hr"><title lang="hr">Sve ce Biti Dobro</title><desc lang="hr">Graevinski poduzetnik Matko Bebi priprema se za prezentaciju projekta Metropolis koja e se graditi u naselju Brezovo. Njegova supruga, lijenica Nevenka Augustini Bebi, uri na posao u Bolnicu Zapad gdje je oekuje operacija.</desc><icon src="https://services.sg101.prd.sctv.ch/content/images/tv/broadcast/1664/400.403_genre_w1920.webp"/></programme>
<programme start="20230213223800 +0000" stop="20230213235700 +0000" channel="HRTInternational.hr"><title lang="hr">Lidija Bajuk Tira Les - Tvornica</title></programme>
<programme start="20230213235700 +0000" stop="20230214010100 +0000" channel="HRTInternational.hr"><title lang="hr">Peti Dan</title><icon src="https://services.sg101.prd.sctv.ch/content/images/tv/broadcast/1664/300.317_genre_w1920.webp"/></programme>
<programme start="20230214010100 +0000" stop="20230214010900 +0000" channel="HRTInternational.hr"><title lang="hr">Vijesti Na Spanjolskom Jeziku</title><icon src="https://services.sg101.prd.sctv.ch/content/images/tv/broadcast/1664/700.701_genre_w1920.webp"/></programme>
<programme start="20230214010900 +0000" stop="20230214020300 +0000" channel="HRTInternational.hr"><title lang="hr">Dnevnik 2</title><desc lang="hr">Dnevnik 2.</desc><icon src="https://services.sg101.prd.sctv.ch/content/images/tv/broadcast/1664/700.701_genre_w1920.webp"/></programme>
<programme start="20230214020300 +0000" stop="20230214025800 +0000" channel="HRTInternational.hr"><title lang="hr">cuvar Dvorca</title><desc lang="hr">Dramska serija cuvar dvorca redatelja i scenarista Lukasa Nole govori o Hrvatskoj osamdesetih kada se na politickoj sceni dogadaju promjene koje će krajem desetljeća promijeniti mapu Europe.</desc><icon src="https://services.sg101.prd.sctv.ch/content/images/tv/program/1664/p14573479ih8aa_Iconic_w1920.webp"/></programme>
<programme start="20230214025800 +0000" stop="20230214031300 +0000" channel="HRTInternational.hr"><title lang="hr">Manjinski mozaik</title><desc lang="hr">Ponosno se drže običaja i čuvaju tradiciju starog kraja iz kojeg ih je potjeralo siromaštvo i glad.</desc><icon src="https://services.sg101.prd.sctv.ch/content/images/tv/broadcast/1664/400.412_genre_w1920.webp"/></programme>
<programme start="20230214031300 +0000" stop="20230214032200 +0000" channel="HRTInternational.hr"><title lang="hr">Vijesti na engleskom jeziku</title><icon src="https://services.sg101.prd.sctv.ch/content/images/tv/broadcast/1664/700.701_genre_w1920.webp"/></programme>
<programme start="20230214032200 +0000" stop="20230214041800 +0000" channel="HRTInternational.hr"><title lang="hr">Ususret Dori</title><icon src="https://services.sg101.prd.sctv.ch/content/images/tv/broadcast/1664/700.709_genre_w1920.webp"/></programme>
<programme start="20230214041800 +0000" stop="20230214045900 +0000" channel="HRTInternational.hr"><title lang="hr">Globalna Hrvatska HTV</title><icon src="https://services.sg101.prd.sctv.ch/content/images/tv/broadcast/1664/400.414_genre_w1920.webp"/></programme>
<programme start="20230214045900 +0000" stop="20230214052300 +0000" channel="HRTInternational.hr"><title lang="hr">Otkrivamo Hrvatsku</title><icon src="https://services.sg101.prd.sctv.ch/content/images/tv/broadcast/1664/400.414_genre_w1920.webp"/></programme>
<programme start="20230214052300 +0000" stop="20230214054900 +0000" channel="HRTInternational.hr"><title lang="hr">Turizam.hrt</title><desc lang="hr">U kojoj mjeri koronavirus utjeèe na turistièka kretanja? Kakvo je trenutno stanje rezervacija za Hrvatsku, odgaðaju li se putovanja ili èak otkazuju, otkriva turizam.hrt. U emisiji govorimo i o nastavku gradnje turistièkog imid¾a Hrvatske.</desc><icon src="https://services.sg101.prd.sctv.ch/content/images/tv/broadcast/1664/300.399_genre_w1920.webp"/></programme>
<programme start="20230214054900 +0000" stop="20230214055700 +0000" channel="HRTInternational.hr"><title lang="hr">Vijesti Na Njemačkom Jeziku</title><icon src="https://services.sg101.prd.sctv.ch/content/images/tv/broadcast/1664/400.414_genre_w1920.webp"/></programme>
<programme start="20230214055700 +0000" stop="20230214063800 +0000" channel="HRTInternational.hr"><title lang="hr">Sve ce Biti Dobro</title><desc lang="hr">Graevinski poduzetnik Matko Bebi priprema se za prezentaciju projekta Metropolis koja e se graditi u naselju Brezovo. Njegova supruga, lijenica Nevenka Augustini Bebi, uri na posao u Bolnicu Zapad gdje je oekuje operacija.</desc><icon src="https://services.sg101.prd.sctv.ch/content/images/tv/broadcast/1664/400.403_genre_w1920.webp"/></programme>
<programme start="20230214063800 +0000" stop="20230214075700 +0000" channel="HRTInternational.hr"><title lang="hr">Lidija Bajuk Tira Les - Tvornica</title></programme>
<programme start="20230214075700 +0000" stop="20230214090100 +0000" channel="HRTInternational.hr"><title lang="hr">Peti Dan</title><icon src="https://services.sg101.prd.sctv.ch/content/images/tv/broadcast/1664/300.317_genre_w1920.webp"/></programme>
<programme start="20230214090100 +0000" stop="20230214090900 +0000" channel="HRTInternational.hr"><title lang="hr">Vijesti Na Spanjolskom Jeziku</title><icon src="https://services.sg101.prd.sctv.ch/content/images/tv/broadcast/1664/700.701_genre_w1920.webp"/></programme>
<programme start="20230214090900 +0000" stop="20230214100300 +0000" channel="HRTInternational.hr"><title lang="hr">Dnevnik 2</title><desc lang="hr">Dnevnik 2.</desc><icon src="https://services.sg101.prd.sctv.ch/content/images/tv/broadcast/1664/700.701_genre_w1920.webp"/></programme>
<programme start="20230214100300 +0000" stop="20230214105800 +0000" channel="HRTInternational.hr"><title lang="hr">cuvar Dvorca</title><desc lang="hr">Dramska serija cuvar dvorca redatelja i scenarista Lukasa Nole govori o Hrvatskoj osamdesetih kada se na politickoj sceni dogadaju promjene koje će krajem desetljeća promijeniti mapu Europe.</desc><icon src="https://services.sg101.prd.sctv.ch/content/images/tv/program/1664/p14573479ih8aa_Iconic_w1920.webp"/></programme>
<programme start="20230214105800 +0000" stop="20230214111300 +0000" channel="HRTInternational.hr"><title lang="hr">Manjinski mozaik</title><desc lang="hr">Ponosno se drže običaja i čuvaju tradiciju starog kraja iz kojeg ih je potjeralo siromaštvo i glad.</desc><icon src="https://services.sg101.prd.sctv.ch/content/images/tv/broadcast/1664/400.412_genre_w1920.webp"/></programme>
<programme start="20230214111300 +0000" stop="20230214112200 +0000" channel="HRTInternational.hr"><title lang="hr">Vijesti na engleskom jeziku</title><icon src="https://services.sg101.prd.sctv.ch/content/images/tv/broadcast/1664/700.701_genre_w1920.webp"/></programme>
<programme start="20230214112200 +0000" stop="20230214121800 +0000" channel="HRTInternational.hr"><title lang="hr">Ususret Dori</title><icon src="https://services.sg101.prd.sctv.ch/content/images/tv/broadcast/1664/700.709_genre_w1920.webp"/></programme>
<programme start="20230214121800 +0000" stop="20230214125900 +0000" channel="HRTInternational.hr"><title lang="hr">Globalna Hrvatska HTV</title><icon src="https://services.sg101.prd.sctv.ch/content/images/tv/broadcast/1664/400.414_genre_w1920.webp"/></programme>
<programme start="20230214125900 +0000" stop="20230214132300 +0000" channel="HRTInternational.hr"><title lang="hr">Otkrivamo Hrvatsku</title><icon src="https://services.sg101.prd.sctv.ch/content/images/tv/broadcast/1664/400.414_genre_w1920.webp"/></programme>
<programme start="20230214132300 +0000" stop="20230214134900 +0000" channel="HRTInternational.hr"><title lang="hr">Turizam.hrt</title><desc lang="hr">U kojoj mjeri koronavirus utjeèe na turistièka kretanja? Kakvo je trenutno stanje rezervacija za Hrvatsku, odgaðaju li se putovanja ili èak otkazuju, otkriva turizam.hrt. U emisiji govorimo i o nastavku gradnje turistièkog imid¾a Hrvatske.</desc><icon src="https://services.sg101.prd.sctv.ch/content/images/tv/broadcast/1664/300.399_genre_w1920.webp"/></programme>
<programme start="20230214134900 +0000" stop="20230214135700 +0000" channel="HRTInternational.hr"><title lang="hr">Vijesti Na Njemačkom Jeziku</title><icon src="https://services.sg101.prd.sctv.ch/content/images/tv/broadcast/1664/400.414_genre_w1920.webp"/></programme>
<programme start="20230214135700 +0000" stop="20230214143800 +0000" channel="HRTInternational.hr"><title lang="hr">Sve ce Biti Dobro</title><desc lang="hr">Graevinski poduzetnik Matko Bebi priprema se za prezentaciju projekta Metropolis koja e se graditi u naselju Brezovo. Njegova supruga, lijenica Nevenka Augustini Bebi, uri na posao u Bolnicu Zapad gdje je oekuje operacija.</desc><icon src="https://services.sg101.prd.sctv.ch/content/images/tv/broadcast/1664/400.403_genre_w1920.webp"/></programme>
<programme start="20230214143800 +0000" stop="20230214155700 +0000" channel="HRTInternational.hr"><title lang="hr">Lidija Bajuk Tira Les - Tvornica</title></programme>
<programme start="20230214155700 +0000" stop="20230214170100 +0000" channel="HRTInternational.hr"><title lang="hr">Peti Dan</title><icon src="https://services.sg101.prd.sctv.ch/content/images/tv/broadcast/1664/300.317_genre_w1920.webp"/></programme>
<programme start="20230214170100 +0000" stop="20230214170900 +0000" channel="HRTInternational.hr"><title lang="hr">Vijesti Na Spanjolskom Jeziku</title><icon src="https://services.sg101.prd.sctv.ch/content/images/tv/broadcast/1664/700.701_genre_w1920.webp"/></programme>
<programme start="20230214170900 +0000" stop="20230214180300 +0000" channel="HRTInternational.hr"><title lang="hr">Dnevnik 2</title><desc lang="hr">Dnevnik 2.</desc><icon src="https://services.sg101.prd.sctv.ch/content/images/tv/broadcast/1664/700.701_genre_w1920.webp"/></programme>
<programme start="20230214180300 +0000" stop="20230214185800 +0000" channel="HRTInternational.hr"><title lang="hr">cuvar Dvorca</title><desc lang="hr">Dramska serija cuvar dvorca redatelja i scenarista Lukasa Nole govori o Hrvatskoj osamdesetih kada se na politickoj sceni dogadaju promjene koje će krajem desetljeća promijeniti mapu Europe.</desc><icon src="https://services.sg101.prd.sctv.ch/content/images/tv/program/1664/p14573479ih8aa_Iconic_w1920.webp"/></programme>
<programme start="20230214185800 +0000" stop="20230214191300 +0000" channel="HRTInternational.hr"><title lang="hr">Manjinski mozaik</title><desc lang="hr">Ponosno se drže običaja i čuvaju tradiciju starog kraja iz kojeg ih je potjeralo siromaštvo i glad.</desc><icon src="https://services.sg101.prd.sctv.ch/content/images/tv/broadcast/1664/400.412_genre_w1920.webp"/></programme>
<programme start="20230214191300 +0000" stop="20230214192200 +0000" channel="HRTInternational.hr"><title lang="hr">Vijesti na engleskom jeziku</title><icon src="https://services.sg101.prd.sctv.ch/content/images/tv/broadcast/1664/700.701_genre_w1920.webp"/></programme>
<programme start="20230214192200 +0000" stop="20230214201800 +0000" channel="HRTInternational.hr"><title lang="hr">Ususret Dori</title><icon src="https://services.sg101.prd.sctv.ch/content/images/tv/broadcast/1664/700.709_genre_w1920.webp"/></programme>
<programme start="20230214201800 +0000" stop="20230214205900 +0000" channel="HRTInternational.hr"><title lang="hr">Globalna Hrvatska HTV</title><icon src="https://services.sg101.prd.sctv.ch/content/images/tv/broadcast/1664/400.414_genre_w1920.webp"/></programme>
<programme start="20230214205900 +0000" stop="20230214212300 +0000" channel="HRTInternational.hr"><title lang="hr">Otkrivamo Hrvatsku</title><icon src="https://services.sg101.prd.sctv.ch/content/images/tv/broadcast/1664/400.414_genre_w1920.webp"/></programme>
<programme start="20230214212300 +0000" stop="20230214214900 +0000" channel="HRTInternational.hr"><title lang="hr">Turizam.hrt</title><desc lang="hr">U kojoj mjeri koronavirus utjeèe na turistièka kretanja? Kakvo je trenutno stanje rezervacija za Hrvatsku, odgaðaju li se putovanja ili èak otkazuju, otkriva turizam.hrt. U emisiji govorimo i o nastavku gradnje turistièkog imid¾a Hrvatske.</desc><icon src="https://services.sg101.prd.sctv.ch/content/images/tv/broadcast/1664/300.399_genre_w1920.webp"/></programme>
<programme start="20230214214900 +0000" stop="20230214215700 +0000" channel="HRTInternational.hr"><title lang="hr">Vijesti Na Njemačkom Jeziku</title><icon src="https://services.sg101.prd.sctv.ch/content/images/tv/broadcast/1664/400.414_genre_w1920.webp"/></programme>
<programme start="20230214215700 +0000" stop="20230214223800 +0000" channel="HRTInternational.hr"><title lang="hr">Sve ce Biti Dobro</title><desc lang="hr">Graevinski poduzetnik Matko Bebi priprema se za prezentaciju projekta Metropolis koja e se graditi u naselju Brezovo. Njegova supruga, lijenica Nevenka Augustini Bebi, uri na posao u Bolnicu Zapad gdje je oekuje operacija.</desc><icon src="https://services.sg101.prd.sctv.ch/content/images/tv/broadcast/1664/400.403_genre_w1920.webp"/></programme>
<programme start="20230214223800 +0000" stop="20230214235700 +0000" channel="HRTInternational.hr"><title lang="hr">Lidija Bajuk Tira Les - Tvornica</title></programme>
<programme start="20230214235700 +0000" stop="20230215010100 +0000" channel="HRTInternational.hr"><title lang="hr">Peti Dan</title><icon src="https://services.sg101.prd.sctv.ch/content/images/tv/broadcast/1664/300.317_genre_w1920.webp"/></programme>
<programme start="20230212223000 +0000" stop="20230213010000 +0000" channel="Z1.hr"><title lang="hr">Zip-Sredisnje Vijesti</title><icon src="https://services.sg101.prd.sctv.ch/content/images/tv/broadcast/632/700.701_genre_w1920.webp"/></programme>
<programme start="20230213010000 +0000" stop="20230213020500 +0000" channel="Z1.hr"><title lang="hr">Izbor Iz Jutrograma</title><icon src="https://services.sg101.prd.sctv.ch/content/images/tv/broadcast/632/700.701_genre_w1920.webp"/></programme>
<programme start="20230213020500 +0000" stop="20230213023500 +0000" channel="Z1.hr"><title lang="hr">Koncert / Dokumentarni Program</title><icon src="https://services.sg101.prd.sctv.ch/content/images/tv/broadcast/632/400.414_genre_w1920.webp"/></programme>
<programme start="20230213023500 +0000" stop="20230213033000 +0000" channel="Z1.hr"><title lang="hr">Glazbena Zona</title><icon src="https://services.sg101.prd.sctv.ch/content/images/tv/broadcast/632/300.311_genre_w1920.webp"/></programme>
<programme start="20230213033000 +0000" stop="20230213040000 +0000" channel="Z1.hr"><title lang="hr">Rev</title><icon src="https://services.sg101.prd.sctv.ch/content/images/tv/broadcast/632/400.414_genre_w1920.webp"/></programme>
<programme start="20230213040000 +0000" stop="20230213044500 +0000" channel="Z1.hr"><title lang="hr">Za Zivot Bez Boli-Nado</title><icon src="https://services.sg101.prd.sctv.ch/content/images/tv/broadcast/632/400.418_genre_w1920.webp"/></programme>
<programme start="20230213044500 +0000" stop="20230213051500 +0000" channel="Z1.hr"><title lang="hr">Od Polja Do Stola</title><icon src="https://services.sg101.prd.sctv.ch/content/images/tv/broadcast/632/400.414_genre_w1920.webp"/></programme>
<programme start="20230213051500 +0000" stop="20230213065500 +0000" channel="Z1.hr"><title lang="hr">Naglasak Dana</title><icon src="https://services.sg101.prd.sctv.ch/content/images/tv/broadcast/632/300.399_genre_w1920.webp"/></programme>
<programme start="20230213065500 +0000" stop="20230213070000 +0000" channel="Z1.hr"><title lang="hr">Glazba</title><desc lang="hr">Glazba.</desc><icon src="https://services.sg101.prd.sctv.ch/content/images/tv/broadcast/632/400.414_genre_w1920.webp"/></programme>
<programme start="20230213070000 +0000" stop="20230213075000 +0000" channel="Z1.hr"><title lang="hr">Sat Za Zdravlje</title><icon src="https://services.sg101.prd.sctv.ch/content/images/tv/broadcast/632/400.418_genre_w1920.webp"/></programme>
<programme start="20230213075000 +0000" stop="20230213090000 +0000" channel="Z1.hr"><title lang="hr">JUTRO UZ Z1</title><icon src="https://services.sg101.prd.sctv.ch/content/images/tv/broadcast/632/300.399_genre_w1920.webp"/></programme>
<programme start="20230213090000 +0000" stop="20230213091500 +0000" channel="Z1.hr"><title lang="hr">Teletrgovina - Avkk</title><icon src="https://services.sg101.prd.sctv.ch/content/images/tv/broadcast/632/300.399_genre_w1920.webp"/></programme>
<programme start="20230213091500 +0000" stop="20230213092500 +0000" channel="Z1.hr"><title lang="hr">Glazbena Zona</title><icon src="https://services.sg101.prd.sctv.ch/content/images/tv/broadcast/632/300.311_genre_w1920.webp"/></programme>
<programme start="20230213092500 +0000" stop="20230213093000 +0000" channel="Z1.hr"><title lang="hr">Najava Programa</title><desc lang="hr">Najava Programa.</desc><icon src="https://services.sg101.prd.sctv.ch/content/images/tv/broadcast/632/700.701_genre_w1920.webp"/></programme>
<programme start="20230213093000 +0000" stop="20230213094500 +0000" channel="Z1.hr"><title lang="hr">Teletrgovina - Avkk</title><icon src="https://services.sg101.prd.sctv.ch/content/images/tv/broadcast/632/300.399_genre_w1920.webp"/></programme>
<programme start="20230213094500 +0000" stop="20230213101500 +0000" channel="Z1.hr"><title lang="hr">Rev</title><icon src="https://services.sg101.prd.sctv.ch/content/images/tv/broadcast/632/400.414_genre_w1920.webp"/></programme>
<programme start="20230213101500 +0000" stop="20230213103000 +0000" channel="Z1.hr"><title lang="hr">Teletrgovina - Avkk</title><icon src="https://services.sg101.prd.sctv.ch/content/images/tv/broadcast/632/300.399_genre_w1920.webp"/></programme>
<programme start="20230213103000 +0000" stop="20230213103500 +0000" channel="Z1.hr"><title lang="hr">Najava Programa</title><desc lang="hr">Najava Programa.</desc><icon src="https://services.sg101.prd.sctv.ch/content/images/tv/broadcast/632/700.701_genre_w1920.webp"/></programme>
<programme start="20230213103500 +0000" stop="20230213105000 +0000" channel="Z1.hr"><title lang="hr">BCTV</title><icon src="https://services.sg101.prd.sctv.ch/content/images/tv/broadcast/632/700.709_genre_w1920.webp"/></programme>
<programme start="20230213105000 +0000" stop="20230213110000 +0000" channel="Z1.hr"><title lang="hr">Glazbena Zona</title><icon src="https://services.sg101.prd.sctv.ch/content/images/tv/broadcast/632/300.311_genre_w1920.webp"/></programme>
<programme start="20230213110000 +0000" stop="20230213113000 +0000" channel="Z1.hr"><title lang="hr">Zupanijski Periskop</title><icon src="https://services.sg101.prd.sctv.ch/content/images/tv/broadcast/632/300.317_genre_w1920.webp"/></programme>
<programme start="20230213113000 +0000" stop="20230213114500 +0000" channel="Z1.hr"><title lang="hr">Teletrgovina - Avkk</title><icon src="https://services.sg101.prd.sctv.ch/content/images/tv/broadcast/632/300.399_genre_w1920.webp"/></programme>
<programme start="20230213114500 +0000" stop="20230213120000 +0000" channel="Z1.hr"><title lang="hr">BCTV</title><icon src="https://services.sg101.prd.sctv.ch/content/images/tv/broadcast/632/700.709_genre_w1920.webp"/></programme>
<programme start="20230213120000 +0000" stop="20230213121000 +0000" channel="Z1.hr"><title lang="hr">Tv Bljesak</title><icon src="https://services.sg101.prd.sctv.ch/content/images/tv/broadcast/632/300.311_genre_w1920.webp"/></programme>
<programme start="20230213121000 +0000" stop="20230213122000 +0000" channel="Z1.hr"><title lang="hr">Blic Vijesti</title><icon src="https://services.sg101.prd.sctv.ch/content/images/tv/broadcast/632/700.701_genre_w1920.webp"/></programme>
<programme start="20230213122000 +0000" stop="20230213131000 +0000" channel="Z1.hr"><title lang="hr">ZOOM</title><icon src="https://services.sg101.prd.sctv.ch/content/images/tv/broadcast/632/300.311_genre_w1920.webp"/></programme>
<programme start="20230213131000 +0000" stop="20230213132000 +0000" channel="Z1.hr"><title lang="hr">Najava Programa</title><desc lang="hr">Najava Programa.</desc><icon src="https://services.sg101.prd.sctv.ch/content/images/tv/broadcast/632/700.701_genre_w1920.webp"/></programme>
<programme start="20230213132000 +0000" stop="20230213135000 +0000" channel="Z1.hr"><title lang="hr">Poticaj, emisija o poljoprivredi</title><icon src="https://services.sg101.prd.sctv.ch/content/images/tv/broadcast/632/700.702_genre_w1920.webp"/></programme>
<programme start="20230213135000 +0000" stop="20230213140000 +0000" channel="Z1.hr"><title lang="hr">Blic Vijesti</title><icon src="https://services.sg101.prd.sctv.ch/content/images/tv/broadcast/632/700.701_genre_w1920.webp"/></programme>
<programme start="20230213140000 +0000" stop="20230213153000 +0000" channel="Z1.hr"><title lang="hr">DEMOKRACIJA</title><icon src="https://services.sg101.prd.sctv.ch/content/images/tv/broadcast/632/400.414_genre_w1920.webp"/></programme>
<programme start="20230213153000 +0000" stop="20230213154500 +0000" channel="Z1.hr"><title lang="hr">Teletrgovina - Avkk</title><icon src="https://services.sg101.prd.sctv.ch/content/images/tv/broadcast/632/300.399_genre_w1920.webp"/></programme>
<programme start="20230213154500 +0000" stop="20230213161500 +0000" channel="Z1.hr"><title lang="hr">Branitelji Danas</title><icon src="https://services.sg101.prd.sctv.ch/content/images/tv/broadcast/632/300.399_genre_w1920.webp"/></programme>
<programme start="20230213161500 +0000" stop="20230213163000 +0000" channel="Z1.hr"><title lang="hr">Teletrgovina - Avkk</title><icon src="https://services.sg101.prd.sctv.ch/content/images/tv/broadcast/632/300.399_genre_w1920.webp"/></programme>
<programme start="20230213163000 +0000" stop="20230213170000 +0000" channel="Z1.hr"><title lang="hr">Dokumentarni</title><desc lang="hr">Dokumentarni film.</desc><icon src="https://services.sg101.prd.sctv.ch/content/images/tv/broadcast/632/400.414_genre_w1920.webp"/></programme>
<programme start="20230213170000 +0000" stop="20230213173000 +0000" channel="Z1.hr"><title lang="hr">Zip-Sredisnje Vijesti</title><icon src="https://services.sg101.prd.sctv.ch/content/images/tv/broadcast/632/700.701_genre_w1920.webp"/></programme>
<programme start="20230213173000 +0000" stop="20230213174000 +0000" channel="Z1.hr"><title lang="hr">Glazba</title><desc lang="hr">Glazba.</desc><icon src="https://services.sg101.prd.sctv.ch/content/images/tv/broadcast/632/400.414_genre_w1920.webp"/></programme>
<programme start="20230213174000 +0000" stop="20230213175500 +0000" channel="Z1.hr"><title lang="hr">BCTV</title><icon src="https://services.sg101.prd.sctv.ch/content/images/tv/broadcast/632/700.709_genre_w1920.webp"/></programme>
<programme start="20230213175500 +0000" stop="20230213181000 +0000" channel="Z1.hr"><title lang="hr">BCTV</title><icon src="https://services.sg101.prd.sctv.ch/content/images/tv/broadcast/632/700.709_genre_w1920.webp"/></programme>
<programme start="20230213181000 +0000" stop="20230213181500 +0000" channel="Z1.hr"><title lang="hr">Glazba</title><desc lang="hr">Glazba.</desc><icon src="https://services.sg101.prd.sctv.ch/content/images/tv/broadcast/632/400.414_genre_w1920.webp"/></programme>
<programme start="20230213181500 +0000" stop="20230213184500 +0000" channel="Z1.hr"><title lang="hr">Mirovinski Odrezak</title><icon src="https://services.sg101.prd.sctv.ch/content/images/tv/broadcast/632/300.317_genre_w1920.webp"/></programme>
<programme start="20230213184500 +0000" stop="20230213185000 +0000" channel="Z1.hr"><title lang="hr">Glazba</title><desc lang="hr">Glazba.</desc><icon src="https://services.sg101.prd.sctv.ch/content/images/tv/broadcast/632/400.414_genre_w1920.webp"/></programme>
<programme start="20230213185000 +0000" stop="20230213185500 +0000" channel="Z1.hr"><title lang="hr">Naglasak Dana</title><icon src="https://services.sg101.prd.sctv.ch/content/images/tv/broadcast/632/300.399_genre_w1920.webp"/></programme>
<programme start="20230213185500 +0000" stop="20230213190500 +0000" channel="Z1.hr"><title lang="hr">Glazba</title><desc lang="hr">Glazba.</desc><icon src="https://services.sg101.prd.sctv.ch/content/images/tv/broadcast/632/400.414_genre_w1920.webp"/></programme>
<programme start="20230213190500 +0000" stop="20230213200500 +0000" channel="Z1.hr"><title lang="hr">Bujica</title><icon src="https://services.sg101.prd.sctv.ch/content/images/tv/broadcast/632/300.317_genre_w1920.webp"/></programme>
<programme start="20230213200500 +0000" stop="20230213201000 +0000" channel="Z1.hr"><title lang="hr">Glazba</title><desc lang="hr">Glazba.</desc><icon src="https://services.sg101.prd.sctv.ch/content/images/tv/broadcast/632/400.414_genre_w1920.webp"/></programme>
<programme start="20230213201000 +0000" stop="20230213201500 +0000" channel="Z1.hr"><title lang="hr">Blic Vijesti</title><icon src="https://services.sg101.prd.sctv.ch/content/images/tv/broadcast/632/700.701_genre_w1920.webp"/></programme>
<programme start="20230213201500 +0000" stop="20230213202000 +0000" channel="Z1.hr"><title lang="hr">BCTV</title><icon src="https://services.sg101.prd.sctv.ch/content/images/tv/broadcast/632/700.709_genre_w1920.webp"/></programme>
<programme start="20230213202000 +0000" stop="20230213203000 +0000" channel="Z1.hr"><title lang="hr">Glazbeni Broj Dana</title><icon src="https://services.sg101.prd.sctv.ch/content/images/tv/broadcast/632/300.311_genre_w1920.webp"/></programme>
<programme start="20230213203000 +0000" stop="20230213213000 +0000" channel="Z1.hr"><title lang="hr">ZOOM</title><icon src="https://services.sg101.prd.sctv.ch/content/images/tv/broadcast/632/300.311_genre_w1920.webp"/></programme>
<programme start="20230213213000 +0000" stop="20230213223000 +0000" channel="Z1.hr"><title lang="hr">Hrvatske Povijesne Istine</title><icon src="https://services.sg101.prd.sctv.ch/content/images/tv/broadcast/632/300.399_genre_w1920.webp"/></programme>
<programme start="20230213223000 +0000" stop="20230213230000 +0000" channel="Z1.hr"><title lang="hr">Zip-Sredisnje Vijesti</title><icon src="https://services.sg101.prd.sctv.ch/content/images/tv/broadcast/632/700.701_genre_w1920.webp"/></programme>
<programme start="20230213230000 +0000" stop="20230214010000 +0000" channel="Z1.hr"><title lang="hr">Astro</title><icon src="https://services.sg101.prd.sctv.ch/content/images/tv/broadcast/632/300.399_genre_w1920.webp"/></programme>
<programme start="20230214010000 +0000" stop="20230214010400 +0000" channel="Z1.hr"><title lang="hr">Blic Vijesti</title><icon src="https://services.sg101.prd.sctv.ch/content/images/tv/broadcast/632/700.701_genre_w1920.webp"/></programme>
<programme start="20230214010400 +0000" stop="20230214010500 +0000" channel="Z1.hr"><title lang="hr">Odjava programa</title><icon src="https://services.sg101.prd.sctv.ch/content/images/tv/broadcast/632/200.225_genre_w1920.webp"/></programme>
<programme start="20230214010500 +0000" stop="20230214022000 +0000" channel="Z1.hr"><title lang="hr">JUTRO UZ Z1</title><icon src="https://services.sg101.prd.sctv.ch/content/images/tv/broadcast/632/300.399_genre_w1920.webp"/></programme>
<programme start="20230214022000 +0000" stop="20230214032000 +0000" channel="Z1.hr"><title lang="hr">Sat Za Zdravlje</title><icon src="https://services.sg101.prd.sctv.ch/content/images/tv/broadcast/632/400.418_genre_w1920.webp"/></programme>
<programme start="20230214032000 +0000" stop="20230214033000 +0000" channel="Z1.hr"><title lang="hr">Glazbena Zona</title><icon src="https://services.sg101.prd.sctv.ch/content/images/tv/broadcast/632/300.311_genre_w1920.webp"/></programme>
<programme start="20230214033000 +0000" stop="20230214043000 +0000" channel="Z1.hr"><title lang="hr">ZOOM</title><icon src="https://services.sg101.prd.sctv.ch/content/images/tv/broadcast/632/300.311_genre_w1920.webp"/></programme>
<programme start="20230214043000 +0000" stop="20230214070000 +0000" channel="Z1.hr"><title lang="hr">Glazbena Ordinacija</title><icon src="https://services.sg101.prd.sctv.ch/content/images/tv/broadcast/632/300.311_genre_w1920.webp"/></programme>
<programme start="20230214070000 +0000" stop="20230214090000 +0000" channel="Z1.hr"><title lang="hr">JUTRO UZ Z1</title><icon src="https://services.sg101.prd.sctv.ch/content/images/tv/broadcast/632/300.399_genre_w1920.webp"/></programme>
<programme start="20230214090000 +0000" stop="20230214091500 +0000" channel="Z1.hr"><title lang="hr">Teletrgovina - Avkk</title><icon src="https://services.sg101.prd.sctv.ch/content/images/tv/broadcast/632/300.399_genre_w1920.webp"/></programme>
<programme start="20230214091500 +0000" stop="20230214093000 +0000" channel="Z1.hr"><title lang="hr">Glazba</title><desc lang="hr">Glazba.</desc><icon src="https://services.sg101.prd.sctv.ch/content/images/tv/broadcast/632/400.414_genre_w1920.webp"/></programme>
<programme start="20230214093000 +0000" stop="20230214094500 +0000" channel="Z1.hr"><title lang="hr">Teletrgovina - Avkk</title><icon src="https://services.sg101.prd.sctv.ch/content/images/tv/broadcast/632/300.399_genre_w1920.webp"/></programme>
<programme start="20230214094500 +0000" stop="20230214103000 +0000" channel="Z1.hr"><title lang="hr">Argumenti</title><icon src="https://services.sg101.prd.sctv.ch/content/images/tv/broadcast/632/400.414_genre_w1920.webp"/></programme>
<programme start="20230214103000 +0000" stop="20230214113000 +0000" channel="Z1.hr"><title lang="hr">Bujica</title><icon src="https://services.sg101.prd.sctv.ch/content/images/tv/broadcast/632/300.317_genre_w1920.webp"/></programme>
<programme start="20230214113000 +0000" stop="20230214114500 +0000" channel="Z1.hr"><title lang="hr">Glazbena Zona</title><icon src="https://services.sg101.prd.sctv.ch/content/images/tv/broadcast/632/300.311_genre_w1920.webp"/></programme>
<programme start="20230214114500 +0000" stop="20230214120000 +0000" channel="Z1.hr"><title lang="hr">Teletrgovina - Avkk</title><icon src="https://services.sg101.prd.sctv.ch/content/images/tv/broadcast/632/300.399_genre_w1920.webp"/></programme>
<programme start="20230214120000 +0000" stop="20230214121000 +0000" channel="Z1.hr"><title lang="hr">Glazba</title><desc lang="hr">Glazba.</desc><icon src="https://services.sg101.prd.sctv.ch/content/images/tv/broadcast/632/400.414_genre_w1920.webp"/></programme>
<programme start="20230214121000 +0000" stop="20230214121500 +0000" channel="Z1.hr"><title lang="hr">Blic Vijesti</title><icon src="https://services.sg101.prd.sctv.ch/content/images/tv/broadcast/632/700.701_genre_w1920.webp"/></programme>
<programme start="20230214121500 +0000" stop="20230214122000 +0000" channel="Z1.hr"><title lang="hr">Glazba</title><desc lang="hr">Glazba.</desc><icon src="https://services.sg101.prd.sctv.ch/content/images/tv/broadcast/632/400.414_genre_w1920.webp"/></programme>
<programme start="20230214122000 +0000" stop="20230214131500 +0000" channel="Z1.hr"><title lang="hr">ZOOM</title><icon src="https://services.sg101.prd.sctv.ch/content/images/tv/broadcast/632/300.311_genre_w1920.webp"/></programme>
<programme start="20230214131500 +0000" stop="20230214132000 +0000" channel="Z1.hr"><title lang="hr">Glazba</title><desc lang="hr">Glazba.</desc><icon src="https://services.sg101.prd.sctv.ch/content/images/tv/broadcast/632/400.414_genre_w1920.webp"/></programme>
<programme start="20230214132000 +0000" stop="20230214135000 +0000" channel="Z1.hr"><title lang="hr">U Dobroj Formi</title><icon src="https://services.sg101.prd.sctv.ch/content/images/tv/broadcast/632/300.311_genre_w1920.webp"/></programme>
<programme start="20230214135000 +0000" stop="20230214135500 +0000" channel="Z1.hr"><title lang="hr">Blic Vijesti</title><icon src="https://services.sg101.prd.sctv.ch/content/images/tv/broadcast/632/700.701_genre_w1920.webp"/></programme>
<programme start="20230214135500 +0000" stop="20230214140000 +0000" channel="Z1.hr"><title lang="hr">Teletrgovina - Avkk</title><icon src="https://services.sg101.prd.sctv.ch/content/images/tv/broadcast/632/300.399_genre_w1920.webp"/></programme>
<programme start="20230214140000 +0000" stop="20230214153000 +0000" channel="Z1.hr"><title lang="hr">DEMOKRACIJA</title><icon src="https://services.sg101.prd.sctv.ch/content/images/tv/broadcast/632/400.414_genre_w1920.webp"/></programme>
<programme start="20230214153000 +0000" stop="20230214160000 +0000" channel="Z1.hr"><title lang="hr">Šarmantni Peking</title><icon src="https://services.sg101.prd.sctv.ch/content/images/tv/broadcast/632/400.414_genre_w1920.webp"/></programme>
<programme start="20230214160000 +0000" stop="20230214163000 +0000" channel="Z1.hr"><title lang="hr">Zupanijski Periskop</title><icon src="https://services.sg101.prd.sctv.ch/content/images/tv/broadcast/632/300.317_genre_w1920.webp"/></programme>
<programme start="20230214163000 +0000" stop="20230214164500 +0000" channel="Z1.hr"><title lang="hr">Teletrgovina - Avkk</title><icon src="https://services.sg101.prd.sctv.ch/content/images/tv/broadcast/632/300.399_genre_w1920.webp"/></programme>
<programme start="20230214164500 +0000" stop="20230214170000 +0000" channel="Z1.hr"><title lang="hr">Glazbena Zona</title><icon src="https://services.sg101.prd.sctv.ch/content/images/tv/broadcast/632/300.311_genre_w1920.webp"/></programme>
<programme start="20230214170000 +0000" stop="20230214173000 +0000" channel="Z1.hr"><title lang="hr">Zip-Sredisnje Vijesti</title><icon src="https://services.sg101.prd.sctv.ch/content/images/tv/broadcast/632/700.701_genre_w1920.webp"/></programme>
<programme start="20230214173000 +0000" stop="20230214173500 +0000" channel="Z1.hr"><title lang="hr">Glazba</title><desc lang="hr">Glazba.</desc><icon src="https://services.sg101.prd.sctv.ch/content/images/tv/broadcast/632/400.414_genre_w1920.webp"/></programme>
<programme start="20230214173500 +0000" stop="20230214180500 +0000" channel="Z1.hr"><title lang="hr">Rijec Na Rijec</title><icon src="https://services.sg101.prd.sctv.ch/content/images/tv/broadcast/632/400.414_genre_w1920.webp"/></programme>
<programme start="20230214180500 +0000" stop="20230214184500 +0000" channel="Z1.hr"><title lang="hr">Time Out</title></programme>
<programme start="20230214184500 +0000" stop="20230214185000 +0000" channel="Z1.hr"><title lang="hr">Glazba</title><desc lang="hr">Glazba.</desc><icon src="https://services.sg101.prd.sctv.ch/content/images/tv/broadcast/632/400.414_genre_w1920.webp"/></programme>
<programme start="20230214185000 +0000" stop="20230214185500 +0000" channel="Z1.hr"><title lang="hr">Naglasak Dana</title><icon src="https://services.sg101.prd.sctv.ch/content/images/tv/broadcast/632/300.399_genre_w1920.webp"/></programme>
<programme start="20230214185500 +0000" stop="20230214190000 +0000" channel="Z1.hr"><title lang="hr">Glazba</title><desc lang="hr">Glazba.</desc><icon src="https://services.sg101.prd.sctv.ch/content/images/tv/broadcast/632/400.414_genre_w1920.webp"/></programme>
<programme start="20230214190000 +0000" stop="20230214200000 +0000" channel="Z1.hr"><title lang="hr">Rendezvous S Ratkom Martinovicem</title><icon src="https://services.sg101.prd.sctv.ch/content/images/tv/broadcast/632/400.414_genre_w1920.webp"/></programme>
<programme start="20230214200000 +0000" stop="20230214201000 +0000" channel="Z1.hr"><title lang="hr">Glazba</title><desc lang="hr">Glazba.</desc><icon src="https://services.sg101.prd.sctv.ch/content/images/tv/broadcast/632/400.414_genre_w1920.webp"/></programme>
<programme start="20230214201000 +0000" stop="20230214201500 +0000" channel="Z1.hr"><title lang="hr">Blic Vijesti</title><icon src="https://services.sg101.prd.sctv.ch/content/images/tv/broadcast/632/700.701_genre_w1920.webp"/></programme>
<programme start="20230214201500 +0000" stop="20230214203000 +0000" channel="Z1.hr"><title lang="hr">Teletrgovina - Avkk</title><icon src="https://services.sg101.prd.sctv.ch/content/images/tv/broadcast/632/300.399_genre_w1920.webp"/></programme>
<programme start="20230214203000 +0000" stop="20230214213000 +0000" channel="Z1.hr"><title lang="hr">ZOOM</title><icon src="https://services.sg101.prd.sctv.ch/content/images/tv/broadcast/632/300.311_genre_w1920.webp"/></programme>
<programme start="20230214213000 +0000" stop="20230214220000 +0000" channel="Z1.hr"><title lang="hr">Kvartura</title><icon src="https://services.sg101.prd.sctv.ch/content/images/tv/broadcast/632/300.399_genre_w1920.webp"/></programme>
<programme start="20230214220000 +0000" stop="20230214223000 +0000" channel="Z1.hr"><title lang="hr">Šarmantni Peking</title><icon src="https://services.sg101.prd.sctv.ch/content/images/tv/broadcast/632/400.414_genre_w1920.webp"/></programme>
<programme start="20230214223000 +0000" stop="20230214230000 +0000" channel="Z1.hr"><title lang="hr">Zip-Sredisnje Vijesti</title><icon src="https://services.sg101.prd.sctv.ch/content/images/tv/broadcast/632/700.701_genre_w1920.webp"/></programme>
<programme start="20230214230000 +0000" stop="20230215010000 +0000" channel="Z1.hr"><title lang="hr">Astro</title><icon src="https://services.sg101.prd.sctv.ch/content/images/tv/broadcast/632/300.399_genre_w1920.webp"/></programme>
</tv>